Metadata-Version: 2.1
Name: pyostra
Version: 0.1.4
Summary: THe internal Python package used for the Ostra projects such as the advanced NFTs generator.
Home-page: https://github.com/yoratoni/pyostra
Author: Yoratoni
Author-email: twingearas@gmail.com
License: BSD
Keywords: ostra internal color colour terminal windows crossplatform
Platform: UNKNOWN
Classifier: Development Status :: 5 - Production/Stable
Classifier: Programming Language :: Python :: 3
Classifier: License :: OSI Approved :: BSD License
Classifier: Intended Audience :: Developers
Classifier: Operating System :: OS Independent
Classifier: Topic :: Terminals
License-File: LICENSE.md
